relcheck/__init__.py
relcheck/__main__.py
relcheck/checks/__init__.py
relcheck/checks/autoscaling/hpa.py
relcheck/checks/cluster/__init__.py
relcheck/checks/cluster/components.py
relcheck/checks/cluster/node.py
relcheck/checks/data/__init__.py
relcheck/checks/data/configmap.py
relcheck/checks/data/pvc.py
relcheck/checks/data/secret.py
relcheck/checks/networking/__init__.py
relcheck/checks/networking/dns.py
relcheck/checks/networking/ingress.py
relcheck/checks/networking/networkpolicy.py
relcheck/checks/networking/service.py
relcheck/checks/nodes/__init__.py
relcheck/checks/nodes/cordon.py
relcheck/checks/pod/__init__.py
relcheck/checks/pod/limits.py
relcheck/checks/pod/runtime.py
relcheck/checks/rbac/clusterrole.py
relcheck/checks/rbac/serviceaccount.py
relcheck/checks/workloads/__init__.py
relcheck/checks/workloads/daemonset.py
relcheck/checks/workloads/deployment.py
relcheck/checks/workloads/scheduling.py
relcheck/checks/workloads/statefulset.py
relcheck/cli.py
relcheck/core/context.py
relcheck/core/discovery.py
relcheck/core/kube.py
relcheck/core/runner.py
relcheck/core/types.py
relcheck/resources/cluster.py
relcheck/resources/data.py
relcheck/resources/namespace.py
relcheck/resources/networking.py
relcheck/resources/nodes.py
relcheck/resources/pod.py
relcheck/resources/rbac.py
relcheck/resources/workloads.py
relcheck-0.1.3.dist-info/METADATA
relcheck-0.1.3.dist-info/WHEEL
relcheck-0.1.3.dist-info/entry_points.txt
relcheck-0.1.3.dist-info/RECORD
