Metadata-Version: 2.3
Name: relcheck
Version: 0.1.3
Summary: CLI diagnostic tool for kubernetes resources
Author: Aditya Ranaut
Requires-Python: >=3.11
Classifier: Programming Language :: Python :: 3
Classifier: Programming Language :: Python :: 3.11
Classifier: Programming Language :: Python :: 3.12
Classifier: Programming Language :: Python :: 3.13
Requires-Dist: click (>=8.2.1,<9.0.0)
Requires-Dist: kubernetes (>=30.1.0,<31.0.0)
